fuzzylogic/__init__.py
fuzzylogic/classes.py
fuzzylogic/combinators.py
fuzzylogic/defuzz.py
fuzzylogic/estimate.py
fuzzylogic/functions.py
fuzzylogic/hedges.py
fuzzylogic/neural_network.py
fuzzylogic/tools.py
fuzzylogic/truth.py
fuzzylogic-1.5.0.dist-info/licenses/LICENSE
fuzzylogic-1.5.0.dist-info/METADATA
fuzzylogic-1.5.0.dist-info/WHEEL
fuzzylogic-1.5.0.dist-info/top_level.txt
fuzzylogic-1.5.0.dist-info/RECORD
