Metadata-Version: 2.4
Name: fuzzylogic
Version: 1.5.0
Summary: Fuzzy Logic for Python 3
Home-page: https://github.com/amogorkon/fuzzylogic
Author: Anselm Kiefner
Author-email: fuzzylogic@anselm.kiefner.de
License: MIT
Keywords: fuzzy logic
Classifier: Development Status :: 5 - Production/Stable
Classifier: Intended Audience :: Developers
Classifier: Intended Audience :: Education
Classifier: Intended Audience :: Manufacturing
Classifier: Intended Audience :: Science/Research
Classifier: Natural Language :: English
Classifier: Operating System :: OS Independent
Classifier: Programming Language :: Python :: 3 :: Only
Classifier: Topic :: Scientific/Engineering :: Artificial Intelligence
Classifier: Topic :: Scientific/Engineering :: Mathematics
Classifier: Topic :: Scientific/Engineering :: Information Analysis
Requires-Python: >=3.12
Provides-Extra: plotting
Requires-Dist: matplotlib; extra == "plotting"
Provides-Extra: numba
Requires-Dist: numba; extra == "numba"
